digitalhub_runtime_container/__init__.py
digitalhub_runtime_container/entities/__init__.py
digitalhub_runtime_container/entities/_base/__init__.py
digitalhub_runtime_container/entities/_base/runtime_entity/__init__.py
digitalhub_runtime_container/entities/_base/runtime_entity/builder.py
digitalhub_runtime_container/entities/_commons/__init__.py
digitalhub_runtime_container/entities/_commons/enums.py
digitalhub_runtime_container/entities/function/__init__.py
digitalhub_runtime_container/entities/function/container/__init__.py
digitalhub_runtime_container/entities/function/container/builder.py
digitalhub_runtime_container/entities/function/container/entity.py
digitalhub_runtime_container/entities/function/container/models.py
digitalhub_runtime_container/entities/function/container/spec.py
digitalhub_runtime_container/entities/function/container/status.py
digitalhub_runtime_container/entities/function/container/utils.py
digitalhub_runtime_container/entities/run/__init__.py
digitalhub_runtime_container/entities/run/_base/__init__.py
digitalhub_runtime_container/entities/run/_base/builder.py
digitalhub_runtime_container/entities/run/_base/entity.py
digitalhub_runtime_container/entities/run/_base/spec.py
digitalhub_runtime_container/entities/run/_base/status.py
digitalhub_runtime_container/entities/run/build/__init__.py
digitalhub_runtime_container/entities/run/build/builder.py
digitalhub_runtime_container/entities/run/build/entity.py
digitalhub_runtime_container/entities/run/build/spec.py
digitalhub_runtime_container/entities/run/build/status.py
digitalhub_runtime_container/entities/run/deploy/__init__.py
digitalhub_runtime_container/entities/run/deploy/builder.py
digitalhub_runtime_container/entities/run/deploy/entity.py
digitalhub_runtime_container/entities/run/deploy/spec.py
digitalhub_runtime_container/entities/run/deploy/status.py
digitalhub_runtime_container/entities/run/job/__init__.py
digitalhub_runtime_container/entities/run/job/builder.py
digitalhub_runtime_container-0.14.0.dist-info/METADATA
digitalhub_runtime_container-0.14.0.dist-info/WHEEL
digitalhub_runtime_container-0.14.0.dist-info/licenses/AUTHORS
digitalhub_runtime_container-0.14.0.dist-info/licenses/LICENSE
digitalhub_runtime_container-0.14.0.dist-info/RECORD
